odoo8_addon_l10n_es_payment_order-8.0.1.7.0.99.dev36-py3.8-nspkg.pth
odoo_addons/l10n_es_payment_order/README.rst
odoo_addons/l10n_es_payment_order/__init__.py
odoo_addons/l10n_es_payment_order/__openerp__.py
odoo_addons/l10n_es_payment_order/data/payment_type_csb.xml
odoo_addons/l10n_es_payment_order/i18n/bg.po
odoo_addons/l10n_es_payment_order/i18n/ca.po
odoo_addons/l10n_es_payment_order/i18n/ca_ES.po
odoo_addons/l10n_es_payment_order/i18n/cs.po
odoo_addons/l10n_es_payment_order/i18n/en_US.po
odoo_addons/l10n_es_payment_order/i18n/es.po
odoo_addons/l10n_es_payment_order/i18n/es_CO.po
odoo_addons/l10n_es_payment_order/i18n/es_CR.po
odoo_addons/l10n_es_payment_order/i18n/eu.po
odoo_addons/l10n_es_payment_order/i18n/fr.po
odoo_addons/l10n_es_payment_order/i18n/gl.po
odoo_addons/l10n_es_payment_order/i18n/hr.po
odoo_addons/l10n_es_payment_order/i18n/l10n_es_payment_order.pot
odoo_addons/l10n_es_payment_order/i18n/nl.po
odoo_addons/l10n_es_payment_order/i18n/pl.po
odoo_addons/l10n_es_payment_order/i18n/pt.po
odoo_addons/l10n_es_payment_order/i18n/pt_BR.po
odoo_addons/l10n_es_payment_order/i18n/ru.po
odoo_addons/l10n_es_payment_order/i18n/sl.po
odoo_addons/l10n_es_payment_order/i18n/sv.po
odoo_addons/l10n_es_payment_order/i18n/tr.po
odoo_addons/l10n_es_payment_order/i18n/vi.po
odoo_addons/l10n_es_payment_order/models/__init__.py
odoo_addons/l10n_es_payment_order/models/payment_mode.py
odoo_addons/l10n_es_payment_order/static/description/icon.png
odoo_addons/l10n_es_payment_order/static/description/icon_src.svg
odoo_addons/l10n_es_payment_order/views/payment_mode_view.xml
odoo_addons/l10n_es_payment_order/wizard/__init__.py
odoo_addons/l10n_es_payment_order/wizard/converter.py
odoo_addons/l10n_es_payment_order/wizard/csb19.py
odoo_addons/l10n_es_payment_order/wizard/csb32.py
odoo_addons/l10n_es_payment_order/wizard/csb34.py
odoo_addons/l10n_es_payment_order/wizard/csb3401.py
odoo_addons/l10n_es_payment_order/wizard/csb58.py
odoo8_addon_l10n_es_payment_order-8.0.1.7.0.99.dev36.dist-info/METADATA
odoo8_addon_l10n_es_payment_order-8.0.1.7.0.99.dev36.dist-info/WHEEL
odoo8_addon_l10n_es_payment_order-8.0.1.7.0.99.dev36.dist-info/namespace_packages.txt
odoo8_addon_l10n_es_payment_order-8.0.1.7.0.99.dev36.dist-info/top_level.txt
odoo8_addon_l10n_es_payment_order-8.0.1.7.0.99.dev36.dist-info/RECORD
