Metadata-Version: 2.1
Name: odoo8-addon-l10n-es-payment-order
Version: 8.0.1.7.0.99.dev36
Summary: Exportación de ficheros bancarios CSB 19, 32, 34 y 58
Home-page: https://github.com/OCA/l10n-spain
Author: Acysos, Serv. Tecnol. Avanzados - Pedro M. Baeza,Odoo Community Association (OCA)
Author-email: support@odoo-community.org
License: AGPL-3
Platform: UNKNOWN
Classifier: Programming Language :: Python
Classifier: Framework :: Odoo
Classifier: Framework :: Odoo :: 8.0
Classifier: License :: OSI Approved :: GNU Affero General Public License v3
Requires-Python: ~=2.7
Requires-Dist: odoo8-addon-account-direct-debit
Requires-Dist: odoo (<9.0a,>=8.0a)
